pycallgraph/__init__.py
pycallgraph/pycallgraph.py
pycallgraph5-0.1.0.dist-info/LICENSE
pycallgraph5-0.1.0.dist-info/WHEEL
pycallgraph5-0.1.0.dist-info/METADATA
pycallgraph5-0.1.0.dist-info/RECORD
