Metadata-Version: 2.1
Name: pycallgraph5
Version: 0.1.0
Summary: 
Author: BuRny
Author-email: gamingburny@gmail.com
Requires-Python: >=3.7,<4.0
Classifier: Programming Language :: Python :: 3
Classifier: Programming Language :: Python :: 3.7
Classifier: Programming Language :: Python :: 3.8
Classifier: Programming Language :: Python :: 3.9
Requires-Dist: aiocontextvars (>=0.2.2,<0.3.0)
Requires-Dist: atomicwrites (>=1.3.0,<2.0.0)
Requires-Dist: contextvars (>=2.4,<3.0)
Requires-Dist: loguru (>=0.5.3,<0.6.0)
Requires-Dist: pyvis (>=0.1.9,<0.2.0)
Requires-Dist: win32-setctime (>=1.0.3,<2.0.0)
